dorsal/__init__.py
dorsal/schema.py
dorsal/serialization.py
dorsal/types.py
dorsal-0.2.0.dist-info/METADATA
dorsal-0.2.0.dist-info/WHEEL
dorsal-0.2.0.dist-info/licenses/LICENSE
dorsal-0.2.0.dist-info/RECORD
